{
  "annotations": { "list": [] },
  "editable": true,
  "graphTooltip": 1,
  "panels": [
    {
      "title": "Request Rate",
      "type": "stat",
      "gridPos": { "h": 4, "w": 6, "x": 0, "y": 0 },
      "datasource": { "type": "prometheus", "uid": "prometheus" },
      "fieldConfig": { "defaults": { "unit": "reqps", "decimals": 1 } },
      "targets": [{ "expr": "sum(rate(http_requests_total[5m]))", "legendFormat": "Requests/s" }]
    },
    {
      "title": "Error Rate",
      "type": "stat",
      "gridPos": { "h": 4, "w": 6, "x": 6, "y": 0 },
      "datasource": { "type": "prometheus", "uid": "prometheus" },
      "fieldConfig": {
        "defaults": {
          "unit": "percentunit", "decimals": 3,
          "thresholds": { "steps": [{ "color": "green", "value": null }, { "color": "red", "value": 0.01 }] }
        }
      },
      "targets": [{ "expr": "sum(rate(http_requests_total{status=~\"5..\"}[5m])) / sum(rate(http_requests_total[5m]))", "legendFormat": "Error Rate" }]
    },
    {
      "title": "Active Connections",
      "type": "stat",
      "gridPos": { "h": 4, "w": 6, "x": 12, "y": 0 },
      "datasource": { "type": "prometheus", "uid": "prometheus" },
      "fieldConfig": { "defaults": { "unit": "short" } },
      "targets": [{ "expr": "app_active_connections", "legendFormat": "Connections" }]
    },
    {
      "title": "Orders Processed",
      "type": "stat",
      "gridPos": { "h": 4, "w": 6, "x": 18, "y": 0 },
      "datasource": { "type": "prometheus", "uid": "prometheus" },
      "fieldConfig": { "defaults": { "unit": "short" } },
      "targets": [{ "expr": "app_orders_processed_total", "legendFormat": "Total Orders" }]
    },
    {
      "title": "Request Rate by Endpoint",
      "type": "timeseries",
      "gridPos": { "h": 8, "w": 12, "x": 0, "y": 4 },
      "datasource": { "type": "prometheus", "uid": "prometheus" },
      "fieldConfig": { "defaults": { "custom": { "fillOpacity": 10 }, "unit": "reqps" } },
      "targets": [{ "expr": "sum(rate(http_requests_total[5m])) by (endpoint)", "legendFormat": "{{ endpoint }}" }]
    },
    {
      "title": "Latency by Endpoint (P99)",
      "type": "timeseries",
      "gridPos": { "h": 8, "w": 12, "x": 12, "y": 4 },
      "datasource": { "type": "prometheus", "uid": "prometheus" },
      "fieldConfig": { "defaults": { "custom": { "fillOpacity": 5 }, "unit": "s" } },
      "targets": [{ "expr": "histogram_quantile(0.99, sum(rate(http_request_duration_seconds_bucket[5m])) by (le, endpoint))", "legendFormat": "{{ endpoint }}" }]
    },
    {
      "title": "Cache Hit Ratio",
      "type": "gauge",
      "gridPos": { "h": 6, "w": 8, "x": 0, "y": 12 },
      "datasource": { "type": "prometheus", "uid": "prometheus" },
      "fieldConfig": {
        "defaults": {
          "unit": "percentunit", "min": 0, "max": 1,
          "thresholds": { "steps": [{ "color": "red", "value": null }, { "color": "yellow", "value": 0.7 }, { "color": "green", "value": 0.9 }] }
        }
      },
      "targets": [{ "expr": "rate(app_cache_hits_total[5m]) / (rate(app_cache_hits_total[5m]) + rate(app_cache_misses_total[5m]))", "legendFormat": "Hit Ratio" }]
    },
    {
      "title": "Database Connections",
      "type": "timeseries",
      "gridPos": { "h": 6, "w": 8, "x": 8, "y": 12 },
      "datasource": { "type": "prometheus", "uid": "prometheus" },
      "fieldConfig": { "defaults": { "unit": "short" } },
      "targets": [{ "expr": "app_db_connections_active", "legendFormat": "Active DB Connections" }]
    },
    {
      "title": "Revenue (Cumulative)",
      "type": "timeseries",
      "gridPos": { "h": 6, "w": 8, "x": 16, "y": 12 },
      "datasource": { "type": "prometheus", "uid": "prometheus" },
      "fieldConfig": { "defaults": { "unit": "currencyUSD", "decimals": 2 } },
      "targets": [{ "expr": "app_revenue_total", "legendFormat": "Total Revenue" }]
    }
  ],
  "refresh": "10s",
  "schemaVersion": 39,
  "tags": ["application", "observability"],
  "time": { "from": "now-1h", "to": "now" },
  "title": "Application Metrics",
  "uid": "app-dashboard"
}
